DoubleLift.py
DoubleLift-0.0.1.dist-info/LICENSE.txt.txt
DoubleLift-0.0.1.dist-info/METADATA
DoubleLift-0.0.1.dist-info/WHEEL
DoubleLift-0.0.1.dist-info/top_level.txt
DoubleLift-0.0.1.dist-info/RECORD
