Metadata-Version: 2.1
Name: DoubleLift
Version: 0.0.1
Summary: Creates Double Lift Charts
Home-page: https://github.com/spencerhs5/DoubleLift-python
Author: Spencer Sadkin
Author-email: spencer.sadkin@gmail.com
License: UNKNOWN
Platform: UNKNOWN
Requires-Dist: pandas (>=0.23.0)
Requires-Dist: numpy (>=1.12.0)
Requires-Dist: seaborn (>=0.10.1)
Requires-Dist: matplotlib (>=3.2.1)
